telegram_notificator/__init__.py
TelegramNotificator-1.0.6.dist-info/LICENCE
TelegramNotificator-1.0.6.dist-info/METADATA
TelegramNotificator-1.0.6.dist-info/WHEEL
TelegramNotificator-1.0.6.dist-info/top_level.txt
TelegramNotificator-1.0.6.dist-info/RECORD
