Metadata-Version: 2.1
Name: TelegramNotificator
Version: 1.0.6
Summary: A basic telegram notifications sender.
Home-page: https://github.com/errais2000/telegram_notificator
Author: Cryptoroid
Author-email: 
License: MIT
Keywords: telegram,message,notification,alert,send message,telegram message,telegram bot
Classifier: Development Status :: 1 - Planning
Classifier: Intended Audience :: Developers
Classifier: Programming Language :: Python :: 3
Classifier: Operating System :: Unix
Classifier: Operating System :: MacOS :: MacOS X
Classifier: Operating System :: Microsoft :: Windows
Classifier: License :: OSI Approved :: MIT License
License-File: LICENCE
Requires-Dist: requests
